{
    "stage_instance": {
        "template_name": "stages/songjiang"
    },
    "default_lighting": "default",
    "object_instances": [
        {
            "template_name": "gate",
            "translation": [
                -0.0,
                1.0,
                -3.0
            ],
            "rotation": [
                1.0,
                0,
                0,
                0
            ],
            "uniform_scale": 1.0,
            "motion_type": "STATIC",
            "translation_origin": "COM"
        },
        {
            "template_name": "gate",
            "translation": [
                1.0,
                1.0,
                -7.0
            ],
            "rotation": [
                1.0,
                0,
                0,
                0
            ],
            "uniform_scale": 1.0,
            "motion_type": "STATIC",
            "translation_origin": "COM"
        },
        {
            "template_name": "gate",
            "translation": [
                -1.0,
                1.0,
                -11.0
            ],
            "rotation": [
                1.0,
                0,
                0,
                0
            ],
            "uniform_scale": 1.0,
            "motion_type": "STATIC",
            "translation_origin": "COM"
        },
        {
            "template_name": "gate",
            "translation": [
                0.0,
                1.0,
                -15.0
            ],
            "rotation": [
                1.0,
                0,
                0,
                0
            ],
            "uniform_scale": 1.0,
            "motion_type": "STATIC",
            "translation_origin": "COM"
        },
        {
            "template_name": "0.15_0.15tree",
            "translation": [
                1.1612089407527573,
                0.0,
                -5.2030209457371255
            ],
            "rotation": [
                1.0,
                0.0,
                0.0,
                0.0
            ],
            "uniform_scale": 1.0,
            "motion_type": "STATIC",
            "translation_origin": "COM"
        },
        {
            "template_name": "0.15_0.15tree",
            "translation": [
                0.47142180336821005,
                0.0,
                -3.8158640959041676
            ],
            "rotation": [
                1.0,
                0.0,
                0.0,
                0.0
            ],
            "uniform_scale": 1.0,
            "motion_type": "STATIC",
            "translation_origin": "COM"
        },
        {
            "template_name": "0.15_0.15tree",
            "translation": [
                1.3427719104398417,
                0.0,
                -4.57005363258985
            ],
            "rotation": [
                1.0,
                0.0,
                0.0,
                0.0
            ],
            "uniform_scale": 1.0,
            "motion_type": "STATIC",
            "translation_origin": "COM"
        },
        {
            "template_name": "0.15_0.15tree",
            "translation": [
                0.5301885991073338,
                0.0,
                -8.910058121427491
            ],
            "rotation": [
                1.0,
                0.0,
                0.0,
                0.0
            ],
            "uniform_scale": 1.0,
            "motion_type": "STATIC",
            "translation_origin": "COM"
        },
        {
            "template_name": "0.15_0.15tree",
            "translation": [
                1.482530846326291,
                0.0,
                -9.190865413943456
            ],
            "rotation": [
                1.0,
                0.0,
                0.0,
                0.0
            ],
            "uniform_scale": 1.0,
            "motion_type": "STATIC",
            "translation_origin": "COM"
        },
        {
            "template_name": "0.15_0.15tree",
            "translation": [
                -1.93940597759328,
                0.0,
                -8.408506154643156
            ],
            "rotation": [
                1.0,
                0.0,
                0.0,
                0.0
            ],
            "uniform_scale": 1.0,
            "motion_type": "STATIC",
            "translation_origin": "COM"
        },
        {
            "template_name": "0.15_0.15tree",
            "translation": [
                -1.2027135553332324,
                0.0,
                -14.234130643194773
            ],
            "rotation": [
                1.0,
                0.0,
                0.0,
                0.0
            ],
            "uniform_scale": 1.0,
            "motion_type": "STATIC",
            "translation_origin": "COM"
        },
        {
            "template_name": "0.15_0.15tree",
            "translation": [
                -1.144529614739302,
                0.0,
                -13.444337580052498
            ],
            "rotation": [
                1.0,
                0.0,
                0.0,
                0.0
            ],
            "uniform_scale": 1.0,
            "motion_type": "STATIC",
            "translation_origin": "COM"
        },
        {
            "template_name": "0.15_0.15tree",
            "translation": [
                0.2595571341508447,
                0.0,
                -12.689965651377674
            ],
            "rotation": [
                1.0,
                0.0,
                0.0,
                0.0
            ],
            "uniform_scale": 1.0,
            "motion_type": "STATIC",
            "translation_origin": "COM"
        }
    ],
    "articulated_object_instances": [],
    "user_custom": {
        "bound": [
            [
                0,
                -7,
                0
            ],
            [
                18,
                7,
                5.0
            ]
        ]
    },
    "navmesh_instance": "empty_stage_navmesh"
}