{
    "stage_instance": {
        "template_name": "stages/songjiang"
    },
    "default_lighting": "default",
    "object_instances": [
        {
            "template_name": "gate",
            "translation": [
                -0.0,
                1.0,
                -3.0
            ],
            "rotation": [
                1.0,
                0,
                0,
                0
            ],
            "uniform_scale": 1.0,
            "motion_type": "STATIC",
            "translation_origin": "COM"
        },
        {
            "template_name": "gate",
            "translation": [
                1.0,
                1.0,
                -7.0
            ],
            "rotation": [
                1.0,
                0,
                0,
                0
            ],
            "uniform_scale": 1.0,
            "motion_type": "STATIC",
            "translation_origin": "COM"
        },
        {
            "template_name": "gate",
            "translation": [
                -1.0,
                1.0,
                -11.0
            ],
            "rotation": [
                1.0,
                0,
                0,
                0
            ],
            "uniform_scale": 1.0,
            "motion_type": "STATIC",
            "translation_origin": "COM"
        },
        {
            "template_name": "gate",
            "translation": [
                0.0,
                1.0,
                -15.0
            ],
            "rotation": [
                1.0,
                0,
                0,
                0
            ],
            "uniform_scale": 1.0,
            "motion_type": "STATIC",
            "translation_origin": "COM"
        },
        {
            "template_name": "0.15_0.15tree",
            "translation": [
                0.31191258883358985,
                0.0,
                -3.7928660393960327
            ],
            "rotation": [
                1.0,
                0.0,
                0.0,
                0.0
            ],
            "uniform_scale": 1.0,
            "motion_type": "STATIC",
            "translation_origin": "COM"
        },
        {
            "template_name": "0.15_0.15tree",
            "translation": [
                -0.8222836020206032,
                0.0,
                -4.643238187942093
            ],
            "rotation": [
                1.0,
                0.0,
                0.0,
                0.0
            ],
            "uniform_scale": 1.0,
            "motion_type": "STATIC",
            "translation_origin": "COM"
        },
        {
            "template_name": "0.15_0.15tree",
            "translation": [
                -1.6307432459755056,
                0.0,
                -5.612130852333949
            ],
            "rotation": [
                1.0,
                0.0,
                0.0,
                0.0
            ],
            "uniform_scale": 1.0,
            "motion_type": "STATIC",
            "translation_origin": "COM"
        },
        {
            "template_name": "0.15_0.15tree",
            "translation": [
                -0.829110273756029,
                0.0,
                -8.860842223224003
            ],
            "rotation": [
                1.0,
                0.0,
                0.0,
                0.0
            ],
            "uniform_scale": 1.0,
            "motion_type": "STATIC",
            "translation_origin": "COM"
        },
        {
            "template_name": "0.15_0.15tree",
            "translation": [
                1.9648300981027877,
                0.0,
                -9.401282236389015
            ],
            "rotation": [
                1.0,
                0.0,
                0.0,
                0.0
            ],
            "uniform_scale": 1.0,
            "motion_type": "STATIC",
            "translation_origin": "COM"
        },
        {
            "template_name": "0.15_0.15tree",
            "translation": [
                -1.2274619152865185,
                0.0,
                -8.774867708961505
            ],
            "rotation": [
                1.0,
                0.0,
                0.0,
                0.0
            ],
            "uniform_scale": 1.0,
            "motion_type": "STATIC",
            "translation_origin": "COM"
        },
        {
            "template_name": "0.15_0.15tree",
            "translation": [
                1.5315830982544236,
                0.0,
                -13.382577843864372
            ],
            "rotation": [
                1.0,
                0.0,
                0.0,
                0.0
            ],
            "uniform_scale": 1.0,
            "motion_type": "STATIC",
            "translation_origin": "COM"
        },
        {
            "template_name": "0.15_0.15tree",
            "translation": [
                -1.3686858526919972,
                0.0,
                -12.545522292464929
            ],
            "rotation": [
                1.0,
                0.0,
                0.0,
                0.0
            ],
            "uniform_scale": 1.0,
            "motion_type": "STATIC",
            "translation_origin": "COM"
        },
        {
            "template_name": "0.15_0.15tree",
            "translation": [
                1.4139003834806525,
                0.0,
                -13.71350754105647
            ],
            "rotation": [
                1.0,
                0.0,
                0.0,
                0.0
            ],
            "uniform_scale": 1.0,
            "motion_type": "STATIC",
            "translation_origin": "COM"
        }
    ],
    "articulated_object_instances": [],
    "user_custom": {
        "bound": [
            [
                0,
                -7,
                0
            ],
            [
                18,
                7,
                5.0
            ]
        ]
    },
    "navmesh_instance": "empty_stage_navmesh"
}