{
    "stage_instance": {
        "template_name": "stages/garage_v1"
    },
    "default_lighting": "default",
    "object_instances": [
        {
            "template_name": "gate",
            "translation": [
                -0.0,
                1.0,
                -3.0
            ],
            "rotation": [
                1.0,
                0,
                0,
                0
            ],
            "uniform_scale": 1.0,
            "motion_type": "STATIC",
            "translation_origin": "COM"
        },
        {
            "template_name": "gate",
            "translation": [
                1.0,
                1.0,
                -6.0
            ],
            "rotation": [
                1.0,
                0,
                0,
                0
            ],
            "uniform_scale": 1.0,
            "motion_type": "STATIC",
            "translation_origin": "COM"
        },
        {
            "template_name": "gate",
            "translation": [
                -1.0,
                1.0,
                -9.0
            ],
            "rotation": [
                1.0,
                0,
                0,
                0
            ],
            "uniform_scale": 1.0,
            "motion_type": "STATIC",
            "translation_origin": "COM"
        },
        {
            "template_name": "gate",
            "translation": [
                0.0,
                1.0,
                -12.0
            ],
            "rotation": [
                1.0,
                0,
                0,
                0
            ],
            "uniform_scale": 1.0,
            "motion_type": "STATIC",
            "translation_origin": "COM"
        },
        {
            "template_name": "0.1_0.1_2cylinder",
            "translation": [
                0.434833442051036,
                0.0,
                -3.692869367733263
            ],
            "rotation": [
                1.0,
                0.0,
                0.0,
                0.0
            ],
            "uniform_scale": 1.0,
            "motion_type": "STATIC",
            "translation_origin": "COM"
        },
        {
            "template_name": "0.1_0.1_2cylinder",
            "translation": [
                0.676359911998534,
                0.0,
                -3.5211159475644287
            ],
            "rotation": [
                1.0,
                0.0,
                0.0,
                0.0
            ],
            "uniform_scale": 1.0,
            "motion_type": "STATIC",
            "translation_origin": "COM"
        },
        {
            "template_name": "0.1_0.1_2cylinder",
            "translation": [
                -0.4501732946666197,
                0.0,
                -3.580716223157121
            ],
            "rotation": [
                1.0,
                0.0,
                0.0,
                0.0
            ],
            "uniform_scale": 1.0,
            "motion_type": "STATIC",
            "translation_origin": "COM"
        },
        {
            "template_name": "0.1_0.1_2cylinder",
            "translation": [
                -0.6855781039418523,
                0.0,
                -3.6784975356752705
            ],
            "rotation": [
                1.0,
                0.0,
                0.0,
                0.0
            ],
            "uniform_scale": 1.0,
            "motion_type": "STATIC",
            "translation_origin": "COM"
        },
        {
            "template_name": "0.1_0.1_2cylinder",
            "translation": [
                -0.48402523973606515,
                0.0,
                -7.598662167741641
            ],
            "rotation": [
                1.0,
                0.0,
                0.0,
                0.0
            ],
            "uniform_scale": 1.0,
            "motion_type": "STATIC",
            "translation_origin": "COM"
        },
        {
            "template_name": "0.1_0.1_2cylinder",
            "translation": [
                0.3339899018198442,
                0.0,
                -7.0149080614142845
            ],
            "rotation": [
                1.0,
                0.0,
                0.0,
                0.0
            ],
            "uniform_scale": 1.0,
            "motion_type": "STATIC",
            "translation_origin": "COM"
        },
        {
            "template_name": "0.1_0.1_2cylinder",
            "translation": [
                -0.885066820316943,
                0.0,
                -6.657991837980469
            ],
            "rotation": [
                1.0,
                0.0,
                0.0,
                0.0
            ],
            "uniform_scale": 1.0,
            "motion_type": "STATIC",
            "translation_origin": "COM"
        },
        {
            "template_name": "0.1_0.1_2cylinder",
            "translation": [
                -0.3362800796626173,
                0.0,
                -7.830599001652415
            ],
            "rotation": [
                1.0,
                0.0,
                0.0,
                0.0
            ],
            "uniform_scale": 1.0,
            "motion_type": "STATIC",
            "translation_origin": "COM"
        },
        {
            "template_name": "0.1_0.1_2cylinder",
            "translation": [
                -0.830317826198266,
                0.0,
                -9.824718244265963
            ],
            "rotation": [
                1.0,
                0.0,
                0.0,
                0.0
            ],
            "uniform_scale": 1.0,
            "motion_type": "STATIC",
            "translation_origin": "COM"
        },
        {
            "template_name": "0.1_0.1_2cylinder",
            "translation": [
                0.6423960514512908,
                0.0,
                -10.973751375252386
            ],
            "rotation": [
                1.0,
                0.0,
                0.0,
                0.0
            ],
            "uniform_scale": 1.0,
            "motion_type": "STATIC",
            "translation_origin": "COM"
        },
        {
            "template_name": "0.1_0.1_2cylinder",
            "translation": [
                0.27624167902574337,
                0.0,
                -9.531429079762031
            ],
            "rotation": [
                1.0,
                0.0,
                0.0,
                0.0
            ],
            "uniform_scale": 1.0,
            "motion_type": "STATIC",
            "translation_origin": "COM"
        },
        {
            "template_name": "0.1_0.1_2cylinder",
            "translation": [
                0.8487124400715729,
                0.0,
                -10.470758298226428
            ],
            "rotation": [
                1.0,
                0.0,
                0.0,
                0.0
            ],
            "uniform_scale": 1.0,
            "motion_type": "STATIC",
            "translation_origin": "COM"
        }
    ],
    "articulated_object_instances": [],
    "user_custom": {
        "bound": [
            [
                0,
                -7,
                0
            ],
            [
                18,
                7,
                5.0
            ]
        ]
    },
    "navmesh_instance": "empty_stage_navmesh"
}