{
    "stage_instance": {
        "template_name": "stages/garage_v1"
    },
    "default_lighting": "default",
    "object_instances": [
        {
            "template_name": "gate",
            "translation": [
                -0.0,
                1.0,
                -3.0
            ],
            "rotation": [
                1.0,
                0,
                0,
                0
            ],
            "uniform_scale": 1.0,
            "motion_type": "STATIC",
            "translation_origin": "COM"
        },
        {
            "template_name": "gate",
            "translation": [
                1.0,
                1.0,
                -6.0
            ],
            "rotation": [
                1.0,
                0,
                0,
                0
            ],
            "uniform_scale": 1.0,
            "motion_type": "STATIC",
            "translation_origin": "COM"
        },
        {
            "template_name": "gate",
            "translation": [
                -1.0,
                1.0,
                -9.0
            ],
            "rotation": [
                1.0,
                0,
                0,
                0
            ],
            "uniform_scale": 1.0,
            "motion_type": "STATIC",
            "translation_origin": "COM"
        },
        {
            "template_name": "gate",
            "translation": [
                0.0,
                1.0,
                -12.0
            ],
            "rotation": [
                1.0,
                0,
                0,
                0
            ],
            "uniform_scale": 1.0,
            "motion_type": "STATIC",
            "translation_origin": "COM"
        },
        {
            "template_name": "0.1_0.1_2cylinder",
            "translation": [
                -0.5004847075230248,
                0.0,
                -4.412050237525743
            ],
            "rotation": [
                1.0,
                0.0,
                0.0,
                0.0
            ],
            "uniform_scale": 1.0,
            "motion_type": "STATIC",
            "translation_origin": "COM"
        },
        {
            "template_name": "0.1_0.1_2cylinder",
            "translation": [
                0.39334993002231355,
                0.0,
                -3.8933811704185306
            ],
            "rotation": [
                1.0,
                0.0,
                0.0,
                0.0
            ],
            "uniform_scale": 1.0,
            "motion_type": "STATIC",
            "translation_origin": "COM"
        },
        {
            "template_name": "0.1_0.1_2cylinder",
            "translation": [
                0.8325714360526717,
                0.0,
                -4.508462144831951
            ],
            "rotation": [
                1.0,
                0.0,
                0.0,
                0.0
            ],
            "uniform_scale": 1.0,
            "motion_type": "STATIC",
            "translation_origin": "COM"
        },
        {
            "template_name": "0.1_0.1_2cylinder",
            "translation": [
                -0.10144725533794063,
                0.0,
                -4.725768478327625
            ],
            "rotation": [
                1.0,
                0.0,
                0.0,
                0.0
            ],
            "uniform_scale": 1.0,
            "motion_type": "STATIC",
            "translation_origin": "COM"
        },
        {
            "template_name": "0.1_0.1_2cylinder",
            "translation": [
                0.3641668088669061,
                0.0,
                -7.353722626432957
            ],
            "rotation": [
                1.0,
                0.0,
                0.0,
                0.0
            ],
            "uniform_scale": 1.0,
            "motion_type": "STATIC",
            "translation_origin": "COM"
        },
        {
            "template_name": "0.1_0.1_2cylinder",
            "translation": [
                0.6423394904771609,
                0.0,
                -7.993788488622577
            ],
            "rotation": [
                1.0,
                0.0,
                0.0,
                0.0
            ],
            "uniform_scale": 1.0,
            "motion_type": "STATIC",
            "translation_origin": "COM"
        },
        {
            "template_name": "0.1_0.1_2cylinder",
            "translation": [
                0.8101873373844095,
                0.0,
                -7.707052275138397
            ],
            "rotation": [
                1.0,
                0.0,
                0.0,
                0.0
            ],
            "uniform_scale": 1.0,
            "motion_type": "STATIC",
            "translation_origin": "COM"
        },
        {
            "template_name": "0.1_0.1_2cylinder",
            "translation": [
                -0.8392897903895438,
                0.0,
                -6.997040888230804
            ],
            "rotation": [
                1.0,
                0.0,
                0.0,
                0.0
            ],
            "uniform_scale": 1.0,
            "motion_type": "STATIC",
            "translation_origin": "COM"
        },
        {
            "template_name": "0.1_0.1_2cylinder",
            "translation": [
                -0.6312545036035664,
                0.0,
                -10.192837101681041
            ],
            "rotation": [
                1.0,
                0.0,
                0.0,
                0.0
            ],
            "uniform_scale": 1.0,
            "motion_type": "STATIC",
            "translation_origin": "COM"
        },
        {
            "template_name": "0.1_0.1_2cylinder",
            "translation": [
                -0.4847157670032165,
                0.0,
                -9.735415873678352
            ],
            "rotation": [
                1.0,
                0.0,
                0.0,
                0.0
            ],
            "uniform_scale": 1.0,
            "motion_type": "STATIC",
            "translation_origin": "COM"
        },
        {
            "template_name": "0.1_0.1_2cylinder",
            "translation": [
                -0.05731454402719849,
                0.0,
                -10.06562912992866
            ],
            "rotation": [
                1.0,
                0.0,
                0.0,
                0.0
            ],
            "uniform_scale": 1.0,
            "motion_type": "STATIC",
            "translation_origin": "COM"
        },
        {
            "template_name": "0.1_0.1_2cylinder",
            "translation": [
                0.850763373148862,
                0.0,
                -10.21257538481087
            ],
            "rotation": [
                1.0,
                0.0,
                0.0,
                0.0
            ],
            "uniform_scale": 1.0,
            "motion_type": "STATIC",
            "translation_origin": "COM"
        }
    ],
    "articulated_object_instances": [],
    "user_custom": {
        "bound": [
            [
                0,
                -7,
                0
            ],
            [
                18,
                7,
                5.0
            ]
        ]
    },
    "navmesh_instance": "empty_stage_navmesh"
}