{
    "stage_instance": {
        "template_name": "stages/garage_v1"
    },
    "default_lighting": "default",
    "object_instances": [
        {
            "template_name": "gate",
            "translation": [
                -0.0,
                1.0,
                -3.0
            ],
            "rotation": [
                1.0,
                0,
                0,
                0
            ],
            "uniform_scale": 1.0,
            "motion_type": "STATIC",
            "translation_origin": "COM"
        },
        {
            "template_name": "gate",
            "translation": [
                1.0,
                1.0,
                -6.0
            ],
            "rotation": [
                1.0,
                0,
                0,
                0
            ],
            "uniform_scale": 1.0,
            "motion_type": "STATIC",
            "translation_origin": "COM"
        },
        {
            "template_name": "gate",
            "translation": [
                -1.0,
                1.0,
                -9.0
            ],
            "rotation": [
                1.0,
                0,
                0,
                0
            ],
            "uniform_scale": 1.0,
            "motion_type": "STATIC",
            "translation_origin": "COM"
        },
        {
            "template_name": "gate",
            "translation": [
                0.0,
                1.0,
                -12.0
            ],
            "rotation": [
                1.0,
                0,
                0,
                0
            ],
            "uniform_scale": 1.0,
            "motion_type": "STATIC",
            "translation_origin": "COM"
        },
        {
            "template_name": "0.1_0.1_2cylinder",
            "translation": [
                0.792239202906764,
                0.0,
                -4.3816159267404
            ],
            "rotation": [
                1.0,
                0.0,
                0.0,
                0.0
            ],
            "uniform_scale": 1.0,
            "motion_type": "STATIC",
            "translation_origin": "COM"
        },
        {
            "template_name": "0.1_0.1_2cylinder",
            "translation": [
                -0.28391128379478436,
                0.0,
                -3.8184767891527214
            ],
            "rotation": [
                1.0,
                0.0,
                0.0,
                0.0
            ],
            "uniform_scale": 1.0,
            "motion_type": "STATIC",
            "translation_origin": "COM"
        },
        {
            "template_name": "0.1_0.1_2cylinder",
            "translation": [
                -0.6675475205395613,
                0.0,
                -3.605903891254573
            ],
            "rotation": [
                1.0,
                0.0,
                0.0,
                0.0
            ],
            "uniform_scale": 1.0,
            "motion_type": "STATIC",
            "translation_origin": "COM"
        },
        {
            "template_name": "0.1_0.1_2cylinder",
            "translation": [
                0.8505911678947042,
                0.0,
                -4.335497940049239
            ],
            "rotation": [
                1.0,
                0.0,
                0.0,
                0.0
            ],
            "uniform_scale": 1.0,
            "motion_type": "STATIC",
            "translation_origin": "COM"
        },
        {
            "template_name": "0.1_0.1_2cylinder",
            "translation": [
                0.09664813370708347,
                0.0,
                -7.713395808160874
            ],
            "rotation": [
                1.0,
                0.0,
                0.0,
                0.0
            ],
            "uniform_scale": 1.0,
            "motion_type": "STATIC",
            "translation_origin": "COM"
        },
        {
            "template_name": "0.1_0.1_2cylinder",
            "translation": [
                -0.02079794671432489,
                0.0,
                -7.594043803381465
            ],
            "rotation": [
                1.0,
                0.0,
                0.0,
                0.0
            ],
            "uniform_scale": 1.0,
            "motion_type": "STATIC",
            "translation_origin": "COM"
        },
        {
            "template_name": "0.1_0.1_2cylinder",
            "translation": [
                0.5614913269997925,
                0.0,
                -6.693548605122981
            ],
            "rotation": [
                1.0,
                0.0,
                0.0,
                0.0
            ],
            "uniform_scale": 1.0,
            "motion_type": "STATIC",
            "translation_origin": "COM"
        },
        {
            "template_name": "0.1_0.1_2cylinder",
            "translation": [
                -0.37157961430107744,
                0.0,
                -7.474662198768165
            ],
            "rotation": [
                1.0,
                0.0,
                0.0,
                0.0
            ],
            "uniform_scale": 1.0,
            "motion_type": "STATIC",
            "translation_origin": "COM"
        },
        {
            "template_name": "0.1_0.1_2cylinder",
            "translation": [
                0.37484103662318513,
                0.0,
                -10.852145564381457
            ],
            "rotation": [
                1.0,
                0.0,
                0.0,
                0.0
            ],
            "uniform_scale": 1.0,
            "motion_type": "STATIC",
            "translation_origin": "COM"
        },
        {
            "template_name": "0.1_0.1_2cylinder",
            "translation": [
                0.7080489026636232,
                0.0,
                -10.819205420556838
            ],
            "rotation": [
                1.0,
                0.0,
                0.0,
                0.0
            ],
            "uniform_scale": 1.0,
            "motion_type": "STATIC",
            "translation_origin": "COM"
        },
        {
            "template_name": "0.1_0.1_2cylinder",
            "translation": [
                0.9738462129928644,
                0.0,
                -9.858580863073836
            ],
            "rotation": [
                1.0,
                0.0,
                0.0,
                0.0
            ],
            "uniform_scale": 1.0,
            "motion_type": "STATIC",
            "translation_origin": "COM"
        },
        {
            "template_name": "0.1_0.1_2cylinder",
            "translation": [
                -0.36180450048584767,
                0.0,
                -10.269255870901977
            ],
            "rotation": [
                1.0,
                0.0,
                0.0,
                0.0
            ],
            "uniform_scale": 1.0,
            "motion_type": "STATIC",
            "translation_origin": "COM"
        }
    ],
    "articulated_object_instances": [],
    "user_custom": {
        "bound": [
            [
                0,
                -7,
                0
            ],
            [
                18,
                7,
                5.0
            ]
        ]
    },
    "navmesh_instance": "empty_stage_navmesh"
}